faster/__init__.py
faster/comparison.py
faster/deduplication.py
faster/estimation.py
faster/evaluation.py
faster/linkage.py
faster/search.py
fast_er_link-0.2.0.dist-info/LICENSE.txt
fast_er_link-0.2.0.dist-info/METADATA
fast_er_link-0.2.0.dist-info/WHEEL
fast_er_link-0.2.0.dist-info/top_level.txt
fast_er_link-0.2.0.dist-info/RECORD
